CreatePackage/__init__.py
CreatePackage/asgi.py
CreatePackage/settings.py
CreatePackage/urls.py
CreatePackage/wsgi.py
package-rabbi-1Cal1/__init__.py
package_rabbi_1Cal1-0.1.dist-info/LICENCE.txt
package_rabbi_1Cal1-0.1.dist-info/METADATA
package_rabbi_1Cal1-0.1.dist-info/WHEEL
package_rabbi_1Cal1-0.1.dist-info/top_level.txt
package_rabbi_1Cal1-0.1.dist-info/RECORD
